{
    "version": "0.4",
    "title": "Block: Gifts",
    "type": "section",
    "metadata": {
        "template_type": "section-other",
        "include_in_zip": "1",
        "elementor_pro_required": "1",
        "wp_page_template": "elementor_header_footer"
    },
    "content": [
        {
            "id": "5d107887",
            "settings": {
                "gap": "no",
                "margin": {
                    "unit": "px",
                    "top": "0",
                    "right": 0,
                    "bottom": "0",
                    "left": 0,
                    "isLinked": false
                },
                "margin_tablet": {
                    "unit": "px",
                    "top": "0",
                    "right": 0,
                    "bottom": "0",
                    "left": 0,
                    "isLinked": false
                },
                "margin_mobile": {
                    "unit": "px",
                    "top": "0",
                    "right": 0,
                    "bottom": "0",
                    "left": 0,
                    "isLinked": false
                },
                "padding": {
                    "unit": "px",
                    "top": "160",
                    "right": "0",
                    "bottom": "160",
                    "left": "0",
                    "isLinked": false
                },
                "padding_tablet": {
                    "unit": "px",
                    "top": "80",
                    "right": "50",
                    "bottom": "80",
                    "left": "50",
                    "isLinked": false
                },
                "padding_mobile": {
                    "unit": "px",
                    "top": "60",
                    "right": "20",
                    "bottom": "60",
                    "left": "20",
                    "isLinked": false
                },
                "_title": "Gifts",
                "background_background": "classic",
                "background_color": "#F5F8F2",
                "__globals__": {
                    "background_color": ""
                }
            },
            "elements": [
                {
                    "id": "6f5c82f3",
                    "settings": {
                        "_column_size": 100,
                        "_inline_size": null,
                        "space_between_widgets": 0
                    },
                    "elements": [
                        {
                            "id": "6923ad09",
                            "settings": {
                                "text": "Divider",
                                "weight": {
                                    "unit": "px",
                                    "size": 2,
                                    "sizes": []
                                },
                                "pattern_height": {
                                    "unit": "px",
                                    "size": 8,
                                    "sizes": []
                                },
                                "gap": {
                                    "unit": "px",
                                    "size": 0,
                                    "sizes": []
                                },
                                "__globals__": {
                                    "color": "globals\/colors?id=accent"
                                },
                                "width": {
                                    "unit": "px",
                                    "size": 70,
                                    "sizes": []
                                },
                                "width_tablet": {
                                    "unit": "px",
                                    "size": 56,
                                    "sizes": []
                                },
                                "_margin_tablet": {
                                    "unit": "px",
                                    "top": "0",
                                    "right": "0",
                                    "bottom": "4",
                                    "left": "0",
                                    "isLinked": false
                                },
                                "_animation": "zoomIn",
                                "_animation_tablet": "none",
                                "_animation_mobile": "none",
                                "_element_width": "auto",
                                "width_mobile": {
                                    "unit": "px",
                                    "size": 46,
                                    "sizes": []
                                },
                                "align": "left",
                                "_position": "absolute",
                                "_offset_x": {
                                    "unit": "px",
                                    "size": 342,
                                    "sizes": []
                                },
                                "_offset_x_tablet": {
                                    "unit": "px",
                                    "size": 150,
                                    "sizes": []
                                },
                                "_offset_x_mobile": {
                                    "unit": "px",
                                    "size": 10,
                                    "sizes": []
                                },
                                "_offset_y": {
                                    "unit": "px",
                                    "size": 0,
                                    "sizes": []
                                },
                                "_animation_delay": 500,
                                "_margin_mobile": {
                                    "unit": "px",
                                    "top": "0",
                                    "right": "0",
                                    "bottom": "4",
                                    "left": "0",
                                    "isLinked": false
                                },
                                "_offset_y_mobile": {
                                    "unit": "px",
                                    "size": -2,
                                    "sizes": []
                                }
                            },
                            "elements": [],
                            "isInner": false,
                            "widgetType": "divider",
                            "elType": "widget"
                        },
                        {
                            "id": "50aa8e65",
                            "settings": {
                                "title": "Gifts for Tea Lovers",
                                "align": "center",
                                "align_mobile": "center",
                                "_margin": {
                                    "unit": "px",
                                    "top": "0",
                                    "right": "0",
                                    "bottom": "16",
                                    "left": "0",
                                    "isLinked": false
                                },
                                "_margin_tablet": {
                                    "unit": "px",
                                    "top": "0",
                                    "right": "0",
                                    "bottom": "16",
                                    "left": "0",
                                    "isLinked": false
                                },
                                "_padding": {
                                    "unit": "px",
                                    "top": "0",
                                    "right": "0",
                                    "bottom": "0",
                                    "left": "0",
                                    "isLinked": true
                                },
                                "__globals__": {
                                    "title_color": ""
                                }
                            },
                            "elements": [],
                            "isInner": false,
                            "widgetType": "heading",
                            "elType": "widget"
                        },
                        {
                            "id": "2a7325f7",
                            "settings": {
                                "gap": "no",
                                "content_position": "middle",
                                "structure": "30",
                                "margin": {
                                    "unit": "px",
                                    "top": "60",
                                    "right": 0,
                                    "bottom": "0",
                                    "left": 0,
                                    "isLinked": false
                                },
                                "margin_tablet": {
                                    "unit": "px",
                                    "top": "40",
                                    "right": 0,
                                    "bottom": "0",
                                    "left": 0,
                                    "isLinked": false
                                },
                                "margin_mobile": {
                                    "unit": "px",
                                    "top": "30",
                                    "right": 0,
                                    "bottom": "0",
                                    "left": 0,
                                    "isLinked": false
                                }
                            },
                            "elements": [
                                {
                                    "id": "6c7cec10",
                                    "settings": {
                                        "_column_size": 33,
                                        "_inline_size": 25,
                                        "_inline_size_tablet": 30,
                                        "_inline_size_mobile": 100,
                                        "space_between_widgets": 0,
                                        "space_between_widgets_tablet": 0,
                                        "space_between_widgets_mobile": 0,
                                        "margin_tablet": {
                                            "unit": "px",
                                            "top": "0",
                                            "right": "0",
                                            "bottom": "0",
                                            "left": "0",
                                            "isLinked": true
                                        },
                                        "padding_tablet": {
                                            "unit": "px",
                                            "top": "0",
                                            "right": "0",
                                            "bottom": "0",
                                            "left": "0",
                                            "isLinked": true
                                        }
                                    },
                                    "elements": [
                                        {
                                            "id": "59b9e879",
                                            "settings": {
                                                "image": {
                                                    "url": "https:\/\/tabit-elementor.nelly-k.com\/wp-content\/uploads\/2020\/11\/g1.png",
                                                    "id": 2876
                                                },
                                                "title_text": "Step 1",
                                                "description_text": "Turpis massa ornare lectus sit amet est.",
                                                "position": "left",
                                                "title_size": "h6",
                                                "image_space": {
                                                    "unit": "px",
                                                    "size": 8,
                                                    "sizes": []
                                                },
                                                "image_space_mobile": {
                                                    "unit": "px",
                                                    "size": 0,
                                                    "sizes": []
                                                },
                                                "image_size": {
                                                    "unit": "%",
                                                    "size": 40,
                                                    "sizes": []
                                                },
                                                "image_size_mobile": {
                                                    "unit": "%",
                                                    "size": 25,
                                                    "sizes": []
                                                },
                                                "text_align": "left",
                                                "text_align_mobile": "center",
                                                "content_vertical_alignment": "bottom",
                                                "title_bottom_space": {
                                                    "unit": "px",
                                                    "size": 8,
                                                    "sizes": []
                                                },
                                                "title_bottom_space_mobile": {
                                                    "unit": "px",
                                                    "size": 8,
                                                    "sizes": []
                                                },
                                                "_margin_tablet": {
                                                    "unit": "px",
                                                    "top": "0",
                                                    "right": "0",
                                                    "bottom": "0",
                                                    "left": "0",
                                                    "isLinked": true
                                                },
                                                "_padding_tablet": {
                                                    "unit": "px",
                                                    "top": "0",
                                                    "right": "0",
                                                    "bottom": "0",
                                                    "left": "0",
                                                    "isLinked": true
                                                },
                                                "_animation": "fadeInLeft",
                                                "_animation_tablet": "none",
                                                "_animation_mobile": "none"
                                            },
                                            "elements": [],
                                            "isInner": false,
                                            "widgetType": "image-box",
                                            "elType": "widget"
                                        },
                                        {
                                            "id": "3c486a4a",
                                            "settings": {
                                                "image": {
                                                    "url": "https:\/\/tabit-elementor.nelly-k.com\/wp-content\/uploads\/2020\/11\/g6.png",
                                                    "id": 2868
                                                },
                                                "title_text": "Step 2",
                                                "description_text": "Turpis massa ornare lectus sit amet est.",
                                                "position": "left",
                                                "title_size": "h6",
                                                "image_space": {
                                                    "unit": "px",
                                                    "size": 8,
                                                    "sizes": []
                                                },
                                                "image_space_mobile": {
                                                    "unit": "px",
                                                    "size": 0,
                                                    "sizes": []
                                                },
                                                "image_size": {
                                                    "unit": "%",
                                                    "size": 40,
                                                    "sizes": []
                                                },
                                                "image_size_mobile": {
                                                    "unit": "%",
                                                    "size": 25,
                                                    "sizes": []
                                                },
                                                "text_align": "left",
                                                "text_align_mobile": "center",
                                                "content_vertical_alignment": "bottom",
                                                "title_bottom_space": {
                                                    "unit": "px",
                                                    "size": 8,
                                                    "sizes": []
                                                },
                                                "title_bottom_space_mobile": {
                                                    "unit": "px",
                                                    "size": 8,
                                                    "sizes": []
                                                },
                                                "_margin": {
                                                    "unit": "px",
                                                    "top": "60",
                                                    "right": "0",
                                                    "bottom": "0",
                                                    "left": "0",
                                                    "isLinked": false
                                                },
                                                "_margin_tablet": {
                                                    "unit": "px",
                                                    "top": "30",
                                                    "right": "0",
                                                    "bottom": "0",
                                                    "left": "0",
                                                    "isLinked": false
                                                },
                                                "_margin_mobile": {
                                                    "unit": "px",
                                                    "top": "20",
                                                    "right": "0",
                                                    "bottom": "0",
                                                    "left": "0",
                                                    "isLinked": false
                                                },
                                                "_animation": "fadeInLeft",
                                                "_animation_tablet": "none",
                                                "_animation_mobile": "none",
                                                "_animation_delay": 400
                                            },
                                            "elements": [],
                                            "isInner": false,
                                            "widgetType": "image-box",
                                            "elType": "widget"
                                        }
                                    ],
                                    "isInner": true,
                                    "elType": "column"
                                },
                                {
                                    "id": "d4e6056",
                                    "settings": {
                                        "_column_size": 33,
                                        "_inline_size": 50,
                                        "_inline_size_tablet": 40,
                                        "space_between_widgets": 0,
                                        "space_between_widgets_tablet": 0,
                                        "background_background": "classic",
                                        "background_image": {
                                            "url": "https:\/\/tabit-elementor.nelly-k.com\/wp-content\/uploads\/2020\/11\/Oval.png",
                                            "id": 2852
                                        },
                                        "background_image_tablet": {
                                            "url": "https:\/\/tabit-elementor.nelly-k.com\/wp-content\/uploads\/2020\/10\/Oval.png",
                                            "id": 1127
                                        },
                                        "background_position": "center center",
                                        "background_position_tablet": "center center",
                                        "background_repeat": "no-repeat",
                                        "background_repeat_tablet": "no-repeat",
                                        "background_size": "contain",
                                        "background_size_tablet": "contain",
                                        "margin": {
                                            "unit": "px",
                                            "top": "0",
                                            "right": "30",
                                            "bottom": "0",
                                            "left": "30",
                                            "isLinked": false
                                        },
                                        "margin_tablet": {
                                            "unit": "px",
                                            "top": "0",
                                            "right": "30",
                                            "bottom": "0",
                                            "left": "20",
                                            "isLinked": false
                                        },
                                        "margin_mobile": {
                                            "unit": "px",
                                            "top": "30",
                                            "right": "0",
                                            "bottom": "30",
                                            "left": "0",
                                            "isLinked": false
                                        },
                                        "padding": {
                                            "unit": "px",
                                            "top": "50",
                                            "right": "0",
                                            "bottom": "50",
                                            "left": "50",
                                            "isLinked": false
                                        },
                                        "padding_tablet": {
                                            "unit": "px",
                                            "top": "30",
                                            "right": "00",
                                            "bottom": "30",
                                            "left": "30",
                                            "isLinked": false
                                        },
                                        "__globals__": {
                                            "background_color": ""
                                        },
                                        "space_between_widgets_mobile": 0
                                    },
                                    "elements": [
                                        {
                                            "id": "1ba96b7c",
                                            "settings": {
                                                "image": {
                                                    "url": "https:\/\/tabit-elementor.nelly-k.com\/wp-content\/uploads\/2020\/10\/Gift-Box.png",
                                                    "id": 1160
                                                },
                                                "_animation": "tada",
                                                "_animation_tablet": "none",
                                                "_animation_mobile": "none",
                                                "_animation_delay": 1500,
                                                "_element_width": "initial",
                                                "_element_width_tablet": "initial",
                                                "_element_width_mobile": "initial",
                                                "_element_custom_width": {
                                                    "unit": "%",
                                                    "size": 90,
                                                    "sizes": []
                                                },
                                                "_element_custom_width_tablet": {
                                                    "unit": "%",
                                                    "size": 110,
                                                    "sizes": []
                                                },
                                                "_element_custom_width_mobile": {
                                                    "unit": "%",
                                                    "size": 90,
                                                    "sizes": []
                                                },
                                                "_position": "absolute",
                                                "_offset_orientation_h": "end",
                                                "_offset_x": {
                                                    "size": 258,
                                                    "unit": "px"
                                                },
                                                "_offset_x_end": {
                                                    "size": -52.421999999999997044142219237983226776123046875,
                                                    "unit": "px"
                                                },
                                                "_offset_x_end_tablet": {
                                                    "size": -39.625,
                                                    "unit": "px"
                                                },
                                                "_offset_x_end_mobile": {
                                                    "size": 3.375,
                                                    "unit": "px"
                                                },
                                                "_offset_y": {
                                                    "size": 219,
                                                    "unit": "px"
                                                },
                                                "_offset_y_tablet": {
                                                    "size": 131,
                                                    "unit": "px"
                                                },
                                                "_offset_y_mobile": {
                                                    "size": 155,
                                                    "unit": "px"
                                                }
                                            },
                                            "elements": [],
                                            "isInner": false,
                                            "widgetType": "image",
                                            "elType": "widget"
                                        },
                                        {
                                            "id": "735bbd41",
                                            "settings": {
                                                "image": {
                                                    "url": "https:\/\/tabit-elementor.nelly-k.com\/wp-content\/uploads\/2020\/10\/Black-Teapot.png",
                                                    "id": 1162
                                                },
                                                "_margin": {
                                                    "unit": "px",
                                                    "top": "0",
                                                    "right": "0",
                                                    "bottom": "0",
                                                    "left": "-100",
                                                    "isLinked": false
                                                },
                                                "_margin_tablet": {
                                                    "unit": "px",
                                                    "top": "0",
                                                    "right": "0",
                                                    "bottom": "0",
                                                    "left": "-80",
                                                    "isLinked": false
                                                },
                                                "_element_width": "auto"
                                            },
                                            "elements": [],
                                            "isInner": false,
                                            "widgetType": "image",
                                            "elType": "widget"
                                        }
                                    ],
                                    "isInner": true,
                                    "elType": "column"
                                },
                                {
                                    "id": "66567c49",
                                    "settings": {
                                        "_column_size": 33,
                                        "_inline_size": 24.6640000000000014779288903810083866119384765625,
                                        "_inline_size_tablet": 30,
                                        "space_between_widgets": 0,
                                        "space_between_widgets_tablet": 0,
                                        "margin_tablet": {
                                            "unit": "px",
                                            "top": "0",
                                            "right": "0",
                                            "bottom": "0",
                                            "left": "0",
                                            "isLinked": false
                                        },
                                        "margin_mobile": {
                                            "unit": "px",
                                            "top": "50",
                                            "right": "0",
                                            "bottom": "0",
                                            "left": "0",
                                            "isLinked": false
                                        }
                                    },
                                    "elements": [
                                        {
                                            "id": "3eadc8cd",
                                            "settings": {
                                                "image": {
                                                    "url": "https:\/\/tabit-elementor.nelly-k.com\/wp-content\/uploads\/2020\/11\/g2.png",
                                                    "id": 2860
                                                },
                                                "title_text": "Step 3",
                                                "description_text": "Turpis massa ornare lectus sit amet est.",
                                                "position": "right",
                                                "title_size": "h6",
                                                "image_space": {
                                                    "unit": "px",
                                                    "size": 8,
                                                    "sizes": []
                                                },
                                                "image_space_mobile": {
                                                    "unit": "px",
                                                    "size": 0,
                                                    "sizes": []
                                                },
                                                "image_size": {
                                                    "unit": "%",
                                                    "size": 40,
                                                    "sizes": []
                                                },
                                                "image_size_mobile": {
                                                    "unit": "%",
                                                    "size": 25,
                                                    "sizes": []
                                                },
                                                "text_align": "left",
                                                "text_align_mobile": "center",
                                                "content_vertical_alignment": "bottom",
                                                "title_bottom_space": {
                                                    "unit": "px",
                                                    "size": 8,
                                                    "sizes": []
                                                },
                                                "title_bottom_space_mobile": {
                                                    "unit": "px",
                                                    "size": 8,
                                                    "sizes": []
                                                },
                                                "_animation": "slideInRight",
                                                "_animation_tablet": "none",
                                                "_animation_mobile": "none",
                                                "_animation_delay": 800,
                                                "_margin_mobile": {
                                                    "unit": "px",
                                                    "top": "0",
                                                    "right": "0",
                                                    "bottom": "0",
                                                    "left": "0",
                                                    "isLinked": true
                                                }
                                            },
                                            "elements": [],
                                            "isInner": false,
                                            "widgetType": "image-box",
                                            "elType": "widget"
                                        },
                                        {
                                            "id": "55b284c",
                                            "settings": {
                                                "image": {
                                                    "url": "https:\/\/tabit-elementor.nelly-k.com\/wp-content\/uploads\/2020\/11\/g3.png",
                                                    "id": 2885
                                                },
                                                "title_text": "Step 4",
                                                "description_text": "Turpis massa ornare lectus sit amet est.",
                                                "position": "right",
                                                "title_size": "h6",
                                                "image_space": {
                                                    "unit": "px",
                                                    "size": 8,
                                                    "sizes": []
                                                },
                                                "image_space_mobile": {
                                                    "unit": "px",
                                                    "size": 0,
                                                    "sizes": []
                                                },
                                                "image_size": {
                                                    "unit": "%",
                                                    "size": 40,
                                                    "sizes": []
                                                },
                                                "image_size_mobile": {
                                                    "unit": "%",
                                                    "size": 25,
                                                    "sizes": []
                                                },
                                                "text_align": "left",
                                                "text_align_mobile": "center",
                                                "content_vertical_alignment": "bottom",
                                                "title_bottom_space": {
                                                    "unit": "px",
                                                    "size": 8,
                                                    "sizes": []
                                                },
                                                "title_bottom_space_mobile": {
                                                    "unit": "px",
                                                    "size": 8,
                                                    "sizes": []
                                                },
                                                "_margin": {
                                                    "unit": "px",
                                                    "top": "60",
                                                    "right": "0",
                                                    "bottom": "0",
                                                    "left": "0",
                                                    "isLinked": false
                                                },
                                                "_margin_tablet": {
                                                    "unit": "px",
                                                    "top": "30",
                                                    "right": "0",
                                                    "bottom": "0",
                                                    "left": "0",
                                                    "isLinked": false
                                                },
                                                "_margin_mobile": {
                                                    "unit": "px",
                                                    "top": "20",
                                                    "right": "0",
                                                    "bottom": "0",
                                                    "left": "0",
                                                    "isLinked": false
                                                },
                                                "_animation": "slideInRight",
                                                "_animation_tablet": "none",
                                                "_animation_mobile": "none",
                                                "_animation_delay": 1200
                                            },
                                            "elements": [],
                                            "isInner": false,
                                            "widgetType": "image-box",
                                            "elType": "widget"
                                        }
                                    ],
                                    "isInner": true,
                                    "elType": "column"
                                }
                            ],
                            "isInner": true,
                            "elType": "section"
                        }
                    ],
                    "isInner": false,
                    "elType": "column"
                }
            ],
            "isInner": false,
            "elType": "section"
        }
    ]
}